auto_modelling/__init__.py
auto_modelling/classification.py
auto_modelling/classifion.py
auto_modelling/preprocess.py
auto_modelling/regression.py
auto_modelling/stack.py
auto_modelling/config/__init__.py
auto_modelling/config/classifier.py
auto_modelling/config/regressor.py
config/__init__.py
config/classifier.py
config/regressor.py
auto_modelling-1.2.5.dist-info/LICENSE
auto_modelling-1.2.5.dist-info/METADATA
auto_modelling-1.2.5.dist-info/WHEEL
auto_modelling-1.2.5.dist-info/top_level.txt
auto_modelling-1.2.5.dist-info/RECORD
