Metadata-Version: 2.1
Name: auto-modelling
Version: 1.2.5
Summary: A light package for automatic model tuning and stacking
Home-page: https://github.com/TangHan54/auto-modelling.git
Author: Tang Han
Author-email: aloofness54@gmail.com
License: UNKNOWN
Platform: UNKNOWN
Classifier: Programming Language :: Python :: 3
Classifier: License :: OSI Approved :: MIT License
Classifier: Operating System :: OS Independent
Requires-Dist: sklearn
Requires-Dist: ipython
Requires-Dist: numpy
Requires-Dist: pandas
Requires-Dist: setuptools
Requires-Dist: xgboost
Requires-Dist: joblib
